acma_orm/__init__.py
acma_orm/database.py
acma_orm/importer.py
acma_orm/models.py
acma_orm/py.typed
acma_orm-0.1.12.dist-info/METADATA
acma_orm-0.1.12.dist-info/WHEEL
acma_orm-0.1.12.dist-info/licenses/LICENSE
acma_orm-0.1.12.dist-info/RECORD
