Metadata-Version: 2.4
Name: acma-orm
Version: 0.1.12
Summary: A Python ORM of the ACMA database
Author-email: JacksonBowe <jacksonbowe98@gmail.com>
License-File: LICENSE
Requires-Python: >=3.12
Requires-Dist: pandas>=2.2.3
Requires-Dist: peewee>=3.17.9
